cantilever/core/__init__.py
cantilever/core/chrono.py
cantilever/core/clipboard.py
cantilever/core/ext_subprocess.py
cantilever/core/options.py
cantilever/core/report.py
cantilever/core/statstream.py
cantilever/core/timer.py
cantilever/plugins/example/__init__.py
cantilever-0.1.0.dist-info/LICENSE
cantilever-0.1.0.dist-info/METADATA
cantilever-0.1.0.dist-info/WHEEL
cantilever-0.1.0.dist-info/top_level.txt
cantilever-0.1.0.dist-info/RECORD
