Metadata-Version: 2.1
Name: cantilever
Version: 0.1.0
Summary: Python toolbox
Home-page: https://cantilever.readthedocs.io
Author: Setepenre
Author-email: setepenre@outlook.com
License: BSD 3-Clause License
Classifier: License :: OSI Approved :: BSD License
Classifier: Programming Language :: Python :: 3.7
Classifier: Programming Language :: Python :: 3.8
Classifier: Programming Language :: Python :: 3.9
Classifier: Operating System :: OS Independent
License-File: LICENSE
Requires-Dist: importlib-resources
Requires-Dist: appdirs
Provides-Extra: all
Requires-Dist: importlib-resources ; extra == 'all'
Provides-Extra: plugins
Requires-Dist: importlib-resources ; extra == 'plugins'
